pymongo_ssh/__init__.py
pymongo_ssh/pymongo_ssh.py
pymongo_ssh-0.0.15.dist-info/LICENSE
pymongo_ssh-0.0.15.dist-info/METADATA
pymongo_ssh-0.0.15.dist-info/WHEEL
pymongo_ssh-0.0.15.dist-info/top_level.txt
pymongo_ssh-0.0.15.dist-info/RECORD
