Metadata-Version: 2.1
Name: pymongo-ssh
Version: 0.0.15
Summary: Python utilities to simplify connection with MongoDB through SSH tunnel
Home-page: https://github.com/pualien/pymongo-ssh
Author: Matteo Senardi
Author-email: pualien@gmail.com
License: MIT
Classifier: License :: OSI Approved :: MIT License
Classifier: Operating System :: OS Independent
Classifier: Programming Language :: Python :: 3.6
Classifier: Programming Language :: Python :: 3.7
Classifier: Programming Language :: Python :: 3.8
Classifier: Programming Language :: Python :: 3.9
Classifier: Programming Language :: Python :: 3.10
Classifier: Topic :: Software Development :: Libraries :: Application Frameworks
Classifier: Topic :: Software Development :: Libraries :: Python Modules
Requires-Python: ~=3.6
License-File: LICENSE
Requires-Dist: pandas >=0.25.3
Requires-Dist: PyYAML >=6.0.1
Requires-Dist: sshtunnel ==0.4.0
Requires-Dist: cryptography >=3.4.3
Requires-Dist: pymongo >=3.11.3
